useful_ts_tools/__init__.py
useful_ts_tools/gen_autoregressive_features.py
useful_ts_tools/gen_temporal_features.py
useful_ts_tools/utils/__init__.py
useful_ts_tools/utils/constants.py
useful_ts_tools/utils/periods.py
useful_ts_tools-0.1.3.dist-info/METADATA
useful_ts_tools-0.1.3.dist-info/WHEEL
useful_ts_tools-0.1.3.dist-info/RECORD
