Metadata-Version: 2.1
Name: useful_ts_tools
Version: 0.1.3
Summary: Utilities to generate useful features for time series
Author: fwo
Requires-Python: >=3.10
Classifier: Programming Language :: Python :: 3
Classifier: Programming Language :: Python :: 3.10
Classifier: Programming Language :: Python :: 3.11
Classifier: Programming Language :: Python :: 3.12
Requires-Dist: holidays (>=0.55)
Requires-Dist: numpy (>=1.16.1)
Requires-Dist: pandas (>=1.5.3)
